docker/Dockerfile
docker/docker-compose.yaml
docker/docker-compose_test.yaml
docker/start-docker-test.sh
docs/requirements.txt
docs/source/Changelog.md
docs/source/License.rst
docs/source/Methode.md
docs/source/conf.py
docs/source/index.rst
docs/source/_static/custom.css
docs/source/_static/favicon.ico
docs/source/_static/logo.png
docs/source/api/api.rst
docs/source/api/cli.rst
docs/source/api/weatherdb.broker.rst
docs/source/api/weatherdb.config.rst
docs/source/api/weatherdb.db.rst
docs/source/api/weatherdb.rst
docs/source/api/weatherdb.station.GroupStation.rst
docs/source/api/weatherdb.station.StationBases.rst
docs/source/api/weatherdb.station.StationET.rst
docs/source/api/weatherdb.station.StationP.rst
docs/source/api/weatherdb.station.StationPD.rst
docs/source/api/weatherdb.station.StationT.rst
docs/source/api/weatherdb.station.rst
docs/source/api/weatherdb.stations.StationsBase.rst
docs/source/api/weatherdb.stations.StationsET.rst
docs/source/api/weatherdb.stations.StationsP.rst
docs/source/api/weatherdb.stations.StationsPD.rst
docs/source/api/weatherdb.stations.StationsT.rst
docs/source/api/weatherdb.stations.rst
docs/source/api/weatherdb.utils.rst
docs/source/setup/Configuration.md
docs/source/setup/Hosting.md
docs/source/setup/Install.md
docs/source/setup/Quickstart.md
docs/source/setup/setup.rst
tests/test-data/test-data-config.ini
tests/test-data/DEM/COP-DEM_GLO-30-DGED__2023_1_clipped.tif
tests/test-data/DEM/README.md
tests/test-data/DEM/eula_F.pdf
tests/test-data/regionalisation/DWD-grid_ma_1991_2020_DGM25_clipped.tif
tests/test-data/regionalisation/HYRAS_ma_1991_2020_DGM25_clipped.tif
tests/test-data/regionalisation/README.md
weatherdb/__init__.py
weatherdb/_version.py
weatherdb/broker.py
weatherdb/cli.py
weatherdb/alembic/README.md
weatherdb/alembic/alembic.ini
weatherdb/alembic/config.py
weatherdb/alembic/env.py
weatherdb/alembic/script.py.mako
weatherdb/alembic/versions/V1.0.0_initial_database_creation.py
weatherdb-1.2.7.dist-info/licenses/LICENSE
weatherdb-1.2.7.dist-info/METADATA
weatherdb-1.2.7.dist-info/WHEEL
weatherdb-1.2.7.dist-info/entry_points.txt
weatherdb-1.2.7.dist-info/top_level.txt
weatherdb-1.2.7.dist-info/RECORD
