Metadata-Version: 2.4
Name: weatherdb
Version: 1.2.7
Summary: This is a package to work with and to create the Weather Database which handles, checks, fills and corrects DWD Weather Station data.
Author-email: Max Schmit <max.schmit@hydrology.uni-freiburg.de>
License:                     GNU GENERAL PUBLIC LICENSE
Project-URL: Homepage, https://gitlab.uni-freiburg.de/hydrology/weatherDB/
Project-URL: Issues, https://gitlab.uni-freiburg.de/hydrology/weatherDB/-/issues
Project-URL: Documentation, https://weatherdb.readthedocs.io/latest/
Classifier: License :: OSI Approved :: GNU General Public License v3 or later (GPLv3+)
Classifier: Programming Language :: Python :: 3.8
Classifier: Programming Language :: Python :: 3.9
Classifier: Programming Language :: Python :: 3.10
Classifier: Programming Language :: Python :: 3.11
Classifier: Programming Language :: Python :: 3.12
Classifier: Programming Language :: Python :: 3.13
Classifier: Topic :: Scientific/Engineering :: Hydrology
Classifier: Topic :: Scientific/Engineering :: Atmospheric Science
Classifier: Intended Audience :: Science/Research
Classifier: Natural Language :: English
Requires-Python: <3.14,>=3.8
License-File: LICENSE
Requires-Dist: geopandas
Requires-Dist: shapely>=2
Requires-Dist: pandas
Requires-Dist: numpy
Requires-Dist: progressbar2
Requires-Dist: rasterio
Requires-Dist: sqlalchemy>2.0
Requires-Dist: psycopg2-binary
Requires-Dist: GeoAlchemy2
Requires-Dist: alembic
Requires-Dist: requests
Requires-Dist: keyring
Requires-Dist: rasterstats
Requires-Dist: click
Requires-Dist: setuptools>=61.0
Requires-Dist: setuptools_scm
Provides-Extra: optionals
Requires-Dist: coloredlogs; extra == "optionals"
Requires-Dist: colorama; extra == "optionals"
Requires-Dist: keyrings.cryptfile; extra == "optionals"
Dynamic: license-file
